pgtest/__init__.py
pgtest/pgtest.py
pgtest-1.3.2.dist-info/LICENSE
pgtest-1.3.2.dist-info/METADATA
pgtest-1.3.2.dist-info/WHEEL
pgtest-1.3.2.dist-info/top_level.txt
pgtest-1.3.2.dist-info/RECORD
