Metadata-Version: 2.1
Name: pgtest
Version: 1.3.2
Summary: Creates a temporary, local PostgreSQL database cluster and server for unittesting, and cleans up after itself
Home-page: https://github.com/jamesnunn/pgtest
Author: James Nunn
Author-email: jamesnunn123@gmail.com
License: MIT
Platform: UNKNOWN
Requires-Dist: pg8000 (>=1.10)
